docs/README_PyPI.md
mlvlab/__init__.py
mlvlab/agents/__init__.py
mlvlab/agents/base.py
mlvlab/agents/q_learning.py
mlvlab/agents/ql/__init__.py
mlvlab/agents/ql/q_learning.py
mlvlab/algorithms/__init__.py
mlvlab/algorithms/registry.py
mlvlab/algorithms/ql/plugin.py
mlvlab/algorithms/random/plugin.py
mlvlab/cli/__init__.py
mlvlab/cli/eval_entry.py
mlvlab/cli/main.py
mlvlab/cli/player_entry.py
mlvlab/cli/run_manager.py
mlvlab/cli/train_entry.py
mlvlab/cli/utils.py
mlvlab/core/__init__.py
mlvlab/core/logic.py
mlvlab/core/player.py
mlvlab/core/trainer.py
mlvlab/envs/__init__.py
mlvlab/envs/ant_lost_v1/adapters.py
mlvlab/envs/ant_lost_v1/config.py
mlvlab/envs/ant_lost_v1/env.py
mlvlab/envs/ant_lost_v1/game.py
mlvlab/envs/ant_lost_v1/renderer.py
mlvlab/envs/ant_lost_v1/reward_wrapper.py
mlvlab/envs/ant_lost_v1/view.py
mlvlab/envs/ant_lost_v1/assets/bump.wav
mlvlab/envs/ant_lost_v1/assets/fail.wav
mlvlab/envs/ant_maze_v1/adapters.py
mlvlab/envs/ant_maze_v1/config.py
mlvlab/envs/ant_maze_v1/env.py
mlvlab/envs/ant_maze_v1/game.py
mlvlab/envs/ant_maze_v1/renderer.py
mlvlab/envs/ant_maze_v1/view.py
mlvlab/envs/ant_maze_v1/assets/bump.wav
mlvlab/envs/ant_maze_v1/assets/create_wall_asset.py
mlvlab/envs/ant_maze_v1/assets/success.wav
mlvlab/envs/ant_maze_v1/assets/tile_wall.png
mlvlab/envs/ant_maze_v1/assets/tile_wall_0.png
mlvlab/envs/ant_maze_v1/assets/tile_wall_1.png
mlvlab/envs/ant_maze_v1/assets/tile_wall_2.png
mlvlab/envs/ant_maze_v1/assets/tile_wall_3.png
mlvlab/envs/ant_maze_v1/assets/tile_wall_4.png
mlvlab/envs/ant_maze_v1/assets/tile_wall_5.png
mlvlab/envs/ant_maze_v1/assets/tile_wall_6.png
mlvlab/envs/ant_maze_v1/assets/tile_wall_7.png
mlvlab/envs/ant_maze_v1/assets/tile_wall_8.png
mlvlab/envs/ant_maze_v1/assets/tile_wall_9.png
mlvlab/envs/ant_scout_v1/__init__.py
mlvlab/envs/ant_scout_v1/adapters.py
mlvlab/envs/ant_scout_v1/config.py
mlvlab/envs/ant_scout_v1/env.py
mlvlab/envs/ant_scout_v1/game.py
mlvlab/envs/ant_scout_v1/renderer.py
mlvlab/envs/ant_scout_v1/view.py
mlvlab-0.2.24.dist-info/licenses/LICENSE.txt
mlvlab-0.2.24.dist-info/METADATA
mlvlab-0.2.24.dist-info/WHEEL
mlvlab-0.2.24.dist-info/entry_points.txt
mlvlab-0.2.24.dist-info/top_level.txt
mlvlab-0.2.24.dist-info/RECORD
